{
  "enabled_exchanges": [
    "Binance",
    "Kraken",
    "KuCoin",
    "Bybit",
    "MEXC",
    "Coinbase",
    "Bitget",
    "Crypto.com",
    "Hyperliquid"
  ],
  "theme": "dark",
  "subaccount_settings": {
    "Binance": {
      "Main": {
        "last_pair": "BTC/USDT"
      },
      "Bot1": {
        "last_pair": "ETH/USDT"
      }
    },
    "Kraken": {
      "Main": {
        "last_pair": "BTC/USDT"
      }
    },
    "KuCoin": {
      "Trading": {
        "last_pair": "SOL/USDT"
      }
    }
  },
  "last_used": {
    "Binance": {
      "subaccount": "Main"
    },
    "Binance:Main": {
      "pair": "BTC/USDT"
    },
    "Binance:Bot1": {
      "pair": "ETH/USDT"
    },
    "Kraken": {
      "subaccount": "Main"
    },
    "Kraken:Main": {
      "pair": "BTC/USDT"
    },
    "KuCoin": {
      "subaccount": "Trading"
    },
    "KuCoin:Trading": {
      "pair": "SOL/USDT"
    }
  }
}
